template_data_project/__init__.py
template_data_project/project_structure.py
template_data_project-0.0.6.dist-info/LICENSE.md
template_data_project-0.0.6.dist-info/METADATA
template_data_project-0.0.6.dist-info/WHEEL
template_data_project-0.0.6.dist-info/top_level.txt
template_data_project-0.0.6.dist-info/RECORD
