Metadata-Version: 2.1
Name: template_data_project
Version: 0.0.6
Summary: data engineering package template involves setting up a directory structure and including essential files and documentation that data engineers can use as a starting point for their projects.
Author-email: ABOULOIFA Najib <najib.abouloifa@gmail.com>
Project-URL: Homepage, https://github.com/ABNajib/data_engineering_template
Classifier: Programming Language :: Python :: 3
Classifier: License :: OSI Approved :: MIT License
Classifier: Operating System :: OS Independent
Requires-Python: >=3.7
License-File: LICENSE.md
